lvec/__init__.py
lvec/backends.py
lvec/caching.py
lvec/exceptions.py
lvec/lvec.py
lvec/utils.py
lvec/vectors.py
lvec/tests/__init__.py
lvec/tests/test_arithmetic.py
lvec/tests/test_boost.py
lvec/tests/test_caching.py
lvec/tests/test_conversions.py
lvec/tests/test_from_constructors.py
lvec/tests/test_init.py
lvec/tests/test_properties.py
lvec/tests/test_shape_error.py
lvec/tests/test_transformations.py
lvec/tests/test_vectors.py
lvec-0.1.4.dist-info/METADATA
lvec-0.1.4.dist-info/WHEEL
lvec-0.1.4.dist-info/licenses/LICENSE
lvec-0.1.4.dist-info/RECORD
