Metadata-Version: 2.4
Name: lvec
Version: 0.1.4
Summary: A package for handling Lorentz vectors with NumPy and Awkward array backends
Project-URL: Homepage, https://github.com/MohamedElashri/lvec
Project-URL: Documentation, https://github.com/MohamedElashri/lvec#readme
Project-URL: Repository, https://github.com/MohamedElashri/lvec
Project-URL: Issues, https://github.com/MohamedElashri/lvec/issues
Author-email: Mohamed Elashri <lvec@elashri.com>
License:                     GNU GENERAL PUBLIC LICENSE
License-File: LICENSE
Keywords: awkward,lorentz,numpy,physics,vector
Classifier: Development Status :: 3 - Alpha
Classifier: Intended Audience :: Science/Research
Classifier: License :: OSI Approved :: GNU General Public License v3 (GPLv3)
Classifier: Programming Language :: Python :: 3
Classifier: Programming Language :: Python :: 3 :: Only
Classifier: Programming Language :: Python :: 3.10
Classifier: Programming Language :: Python :: 3.11
Classifier: Programming Language :: Python :: 3.12
Classifier: Topic :: Scientific/Engineering :: Physics
Requires-Python: >=3.10
Requires-Dist: awkward>=2.0.0
Requires-Dist: numpy>=1.20.0
Provides-Extra: dev
Requires-Dist: pytest>=7.0.0; extra == 'dev'
Requires-Dist: uproot>=5.0.0; extra == 'dev'
